implib2/__init__.py
implib2/__version__.py
implib2/imp_bus.py
implib2/imp_commands.py
implib2/imp_crc.py
implib2/imp_datatypes.py
implib2/imp_device.py
implib2/imp_eeprom.py
implib2/imp_errors.json
implib2/imp_errors.py
implib2/imp_helper.py
implib2/imp_modules.py
implib2/imp_packages.py
implib2/imp_responces.py
implib2/imp_tables.json
implib2/imp_tables.py
implib2-1.0.1.dist-info/DESCRIPTION.rst
implib2-1.0.1.dist-info/METADATA
implib2-1.0.1.dist-info/RECORD
implib2-1.0.1.dist-info/WHEEL
implib2-1.0.1.dist-info/metadata.json
implib2-1.0.1.dist-info/top_level.txt
