Metadata-Version: 2.0
Name: implib2
Version: 1.0.1
Summary: Python implementation of the IMPBUS-2 data transmission protocol.
Home-page: https://github.com/mhubig/implib2
Author: Markus Hubig
Author-email: mh@imko.de
License: MIT
Platform: UNKNOWN
Classifier: License :: OSI Approved :: MIT License
Classifier: Programming Language :: Python
Classifier: Programming Language :: Python :: 2.7
Classifier: Programming Language :: Python :: 3.3
Classifier: Programming Language :: Python :: 3.4
Classifier: Programming Language :: Python :: 3.5
Classifier: Programming Language :: Python :: 3.6
Requires-Dist: pyserial
